{
	"info": {
		"_postman_id": "54b52c58-dfb3-4ec9-b304-d3f7f2e9ee33",
		"name": "e-Commerce bvk",
		"schema": "https://schema.getpostman.com/json/collection/v2.1.0/collection.json"
	},
	"item": [
		{
			"name": "Add New Product",
			"request": {
				"method": "POST",
				"header": [],
				"body": {
					"mode": "raw",
					"raw": "{\r\n    \"name\": \"Teh Botol2\",\r\n    \"brand\": \"sosro\",\r\n    \"quantity\": 1,\r\n    \"code\":\"S123\",\r\n    \"price\": 20000,\r\n    \"image\": \"https://sinarsosro.id/files/images/Banner%20Produk%20TBS-01.jpg\",\r\n    \"expDate\": \"2022-06-28\" \r\n\r\n}",
					"options": {
						"raw": {
							"language": "json"
						}
					}
				},
				"url": {
					"raw": "localhost:8080/product/add",
					"host": [
						"localhost"
					],
					"port": "8080",
					"path": [
						"product",
						"add"
					]
				}
			},
			"response": []
		},
		{
			"name": "Get All Product",
			"request": {
				"method": "GET",
				"header": []
			},
			"response": []
		},
		{
			"name": "Get Product By Id",
			"request": {
				"method": "GET",
				"header": []
			},
			"response": []
		},
		{
			"name": "Delete Product",
			"request": {
				"method": "DELETE",
				"header": [],
				"url": {
					"raw": "localhost:8080/product/deleteProduct?id=2",
					"host": [
						"localhost"
					],
					"port": "8080",
					"path": [
						"product",
						"deleteProduct"
					],
					"query": [
						{
							"key": "id",
							"value": "2"
						}
					]
				}
			},
			"response": []
		},
		{
			"name": "Update Product",
			"request": {
				"method": "PUT",
				"header": [],
				"url": {
					"raw": "localhost:8080/product/getProductById?id=2",
					"host": [
						"localhost"
					],
					"port": "8080",
					"path": [
						"product",
						"getProductById"
					],
					"query": [
						{
							"key": "id",
							"value": "2"
						}
					]
				}
			},
			"response": []
		},
		{
			"name": "Add New user",
			"request": {
				"method": "POST",
				"header": [],
				"url": {
					"raw": "localhost:8080/product/add",
					"host": [
						"localhost"
					],
					"port": "8080",
					"path": [
						"product",
						"add"
					]
				}
			},
			"response": []
		},
		{
			"name": "Add Selected Product to Cart",
			"request": {
				"method": "POST",
				"header": [],
				"url": {
					"raw": "localhost:8080/cart/add",
					"host": [
						"localhost"
					],
					"port": "8080",
					"path": [
						"cart",
						"add"
					]
				}
			},
			"response": []
		},
		{
			"name": "Get All Product In Cart",
			"request": {
				"method": "GET",
				"header": []
			},
			"response": []
		},
		{
			"name": "Get Finalize Total Price",
			"request": {
				"method": "GET",
				"header": []
			},
			"response": []
		},
		{
			"name": "Delete Cart By Id",
			"request": {
				"method": "DELETE",
				"header": []
			},
			"response": []
		}
	]
}